llmling_provider_llm/__init__.py
llmling_provider_llm/client.py
llmling_provider_llm/provider.py
llmling_provider_llm/py.typed
llmling_provider_llm-0.1.0.dist-info/METADATA
llmling_provider_llm-0.1.0.dist-info/WHEEL
llmling_provider_llm-0.1.0.dist-info/entry_points.txt
llmling_provider_llm-0.1.0.dist-info/licenses/LICENSE
llmling_provider_llm-0.1.0.dist-info/RECORD
