Metadata-Version: 2.3
Name: llmling-provider-llm
Version: 0.1.0
Summary: LLMling provider based on the package 'llm'
Project-URL: Documentation, https://phil65.github.io/llmling-provider-llm/
Project-URL: Source, https://github.com/phil65/llmling-provider-llm
Project-URL: Issues, https://github.com/phil65/llmling-provider-llm/issues
Project-URL: Discussions, https://github.com/phil65/llmling-provider-llm/discussions
Project-URL: Code coverage, https://app.codecov.io/gh/phil65/llmling-provider-llm
Author-email: Philipp Temminghoff <philipptemminghoff@googlemail.com>
License: MIT License
Classifier: Development Status :: 4 - Beta
Classifier: Intended Audience :: Developers
Classifier: Operating System :: OS Independent
Classifier: Programming Language :: Python :: 3
Classifier: Programming Language :: Python :: 3 :: Only
Classifier: Programming Language :: Python :: 3.12
Classifier: Programming Language :: Python :: 3.13
Classifier: Programming Language :: Python :: 3.14
Classifier: Topic :: Documentation
Classifier: Topic :: Software Development
Classifier: Topic :: Utilities
Classifier: Typing :: Typed
Requires-Python: >=3.12
Requires-Dist: llm>=0.18
Requires-Dist: llmling>=0.1.1
Requires-Dist: pydantic
